ASV_System/__init__.py
ASV_System/db_utils.py
ASV_System/resnet_blocks.py
ASV_System/resnet_models.py
ASV_System/verification.py
CM_System/AASIST.py
CM_System/AASIST_config.json
CM_System/__init__.py
CM_System/cm_utils.py
CM_System/spoofing_score.py
Weights/AASIST.pth
Weights/ASV_model.pth
Weights/__init__.py
Weights/fusion_model.pkl
Weights/scaler.pkl
sonic_cipher/__init__.py
sonic_cipher-1.0.0.dist-info/licenses/LICENSE
sonic_cipher-1.0.0.dist-info/METADATA
sonic_cipher-1.0.0.dist-info/WHEEL
sonic_cipher-1.0.0.dist-info/top_level.txt
sonic_cipher-1.0.0.dist-info/RECORD
